renameat2/__init__.py
renameat2/_renameat2.abi3.so
renameat2-0.4.4.dist-info/top_level.txt
renameat2-0.4.4.dist-info/WHEEL
renameat2-0.4.4.dist-info/METADATA
renameat2-0.4.4.dist-info/RECORD
renameat2-0.4.4.dist-info/LICENSE
