Metadata-Version: 2.1
Name: renameat2
Version: 0.4.4
Summary: A wrapper around Linux's renameat2 system call
Home-page: https://github.com/jordemort/python-renameat2
Author: Jordan Webb
Author-email: jordan@getseam.com
License: MIT
Project-URL: Documentation, https://python-renameat2.readthedocs.io/
Project-URL: Bug Tracker, https://github.com/jordemort/python-renameat2/issues
Project-URL: Source Code, https://github.com/jordemort/python-renameat2
Keywords: linux,rename,renameat2,overlayfs,atomic,swap,exchange,whiteout
Classifier: Development Status :: 4 - Beta
Classifier: Intended Audience :: Developers
Classifier: License :: OSI Approved :: MIT License
Classifier: Programming Language :: Python
Classifier: Programming Language :: Python :: 3 :: Only
Classifier: Programming Language :: Python :: 3.6
Classifier: Programming Language :: Python :: 3.7
Classifier: Programming Language :: Python :: 3.8
Classifier: Programming Language :: Python :: 3.9
Classifier: Programming Language :: Python :: 3.10
Classifier: Programming Language :: Python :: 3.11
Classifier: Operating System :: POSIX :: Linux
Classifier: Topic :: Software Development :: Libraries
Classifier: Topic :: System :: Filesystems
Requires-Python: >=3.6
License-File: LICENSE
